flowtube/__init__.py
flowtube/__init__.pyi
flowtube/boat_reactor.py
flowtube/coated_wall_reactor.py
flowtube/diffusion_coef.py
flowtube/flow_calc.py
flowtube/py.typed
flowtube/tools.py
flowtube/viscosity_density.py
flowtube-1.1.0.dist-info/licenses/LICENSE
flowtube-1.1.0.dist-info/METADATA
flowtube-1.1.0.dist-info/WHEEL
flowtube-1.1.0.dist-info/top_level.txt
flowtube-1.1.0.dist-info/RECORD
