Metadata-Version: 2.4
Name: flowtube
Version: 1.1.0
Summary: A Python package for transport and diffusion calculations in cylindrical flow reactors
Author-email: Corey Pedersen <coreyped@gmail.com>
License-Expression: MIT
Project-URL: Homepage, https://github.com/c-pedersen/flowtube
Project-URL: Repository, https://github.com/c-pedersen/flowtube
Project-URL: Documentation, https://github.com/c-pedersen/flowtube#readme
Project-URL: Bug Tracker, https://github.com/c-pedersen/flowtube/issues
Keywords: flow reactor,diffusion,transport,coated wall reactor,aerosol,atmospheric chemistry
Classifier: Development Status :: 3 - Alpha
Classifier: Intended Audience :: Science/Research
Classifier: Operating System :: OS Independent
Classifier: Programming Language :: Python :: 3
Classifier: Programming Language :: Python :: 3.7
Classifier: Programming Language :: Python :: 3.8
Classifier: Programming Language :: Python :: 3.9
Classifier: Programming Language :: Python :: 3.10
Classifier: Programming Language :: Python :: 3.11
Classifier: Topic :: Scientific/Engineering :: Chemistry
Classifier: Topic :: Scientific/Engineering :: Physics
Requires-Python: >=3.7
License-File: LICENSE
Requires-Dist: numpy>=1.18.0
Requires-Dist: pandas>=1.0.0
Requires-Dist: tabulate>=0.8.0
Requires-Dist: molmass>=2019.1.1
Requires-Dist: requests>=2.22.0
Provides-Extra: test
Requires-Dist: pytest>=7.0; extra == "test"
Requires-Dist: pytest-cov; extra == "test"
Dynamic: license-file
